{"target_field":"y","_managed_parameters":"[{\"key\":\"x0\",\"type\":\"Float\",\"default\":0.0,\"descritption\":null,\"range\":[-10.0,10.0]},{\"key\":\"x1\",\"type\":\"Float\",\"default\":0.0,\"descritption\":null,\"range\":[-10.0,10.0]},{\"key\":\"x2\",\"type\":\"Float\",\"default\":0.0,\"descritption\":null,\"range\":[-10.0,10.0]},{\"key\":\"x3\",\"type\":\"Float\",\"default\":0.0,\"descritption\":null,\"range\":[-10.0,10.0]},{\"key\":\"x4\",\"type\":\"Float\",\"default\":0.0,\"descritption\":null,\"range\":[-10.0,10.0]},{\"key\":\"x5\",\"type\":\"Float\",\"default\":0.0,\"descritption\":null,\"range\":[-10.0,10.0]},{\"key\":\"x6\",\"type\":\"Float\",\"default\":0.0,\"descritption\":null,\"range\":[-10.0,10.0]},{\"key\":\"x7\",\"type\":\"Float\",\"default\":0.0,\"descritption\":null,\"range\":[-10.0,10.0]},{\"key\":\"x8\",\"type\":\"Float\",\"default\":0.0,\"descritption\":null,\"range\":[-10.0,10.0]},{\"key\":\"x9\",\"type\":\"Float\",\"default\":0.0,\"descritption\":null,\"range\":[-10.0,10.0]},{\"key\":\"x10\",\"type\":\"Float\",\"default\":0.0,\"descritption\":null,\"range\":[-10.0,10.0]},{\"key\":\"x11\",\"type\":\"Float\",\"default\":0.0,\"descritption\":null,\"range\":[-10.0,10.0]},{\"key\":\"x12\",\"type\":\"Float\",\"default\":0.0,\"descritption\":null,\"range\":[-10.0,10.0]},{\"key\":\"x13\",\"type\":\"Float\",\"default\":0.0,\"descritption\":null,\"range\":[-10.0,10.0]},{\"key\":\"x14\",\"type\":\"Float\",\"default\":0.0,\"descritption\":null,\"range\":[-10.0,10.0]},{\"key\":\"x15\",\"type\":\"Float\",\"default\":0.0,\"descritption\":null,\"range\":[-10.0,10.0]},{\"key\":\"x16\",\"type\":\"Float\",\"default\":0.0,\"descritption\":null,\"range\":[-10.0,10.0]},{\"key\":\"x17\",\"type\":\"Float\",\"default\":0.0,\"descritption\":null,\"range\":[-10.0,10.0]},{\"key\":\"x18\",\"type\":\"Float\",\"default\":0.0,\"descritption\":null,\"range\":[-10.0,10.0]},{\"key\":\"x19\",\"type\":\"Float\",\"default\":0.0,\"descritption\":null,\"range\":[-10.0,10.0]},{\"key\":\"x20\",\"type\":\"Float\",\"default\":0.0,\"descritption\":null,\"range\":[-10.0,10.0]},{\"key\":\"x21\",\"type\":\"Float\",\"default\":0.0,\"descritption\":null,\"range\":[-10.0,10.0]},{\"key\":\"x22\",\"type\":\"Float\",\"default\":0.0,\"descritption\":null,\"range\":[-10.0,10.0]},{\"key\":\"x23\",\"type\":\"Float\",\"default\":0.0,\"descritption\":null,\"range\":[-10.0,10.0]},{\"key\":\"x24\",\"type\":\"Float\",\"default\":0.0,\"descritption\":null,\"range\":[-10.0,10.0]},{\"key\":\"x25\",\"type\":\"Float\",\"default\":0.0,\"descritption\":null,\"range\":[-10.0,10.0]},{\"key\":\"x26\",\"type\":\"Float\",\"default\":0.0,\"descritption\":null,\"range\":[-10.0,10.0]},{\"key\":\"x27\",\"type\":\"Float\",\"default\":0.0,\"descritption\":null,\"range\":[-10.0,10.0]},{\"key\":\"x28\",\"type\":\"Float\",\"default\":0.0,\"descritption\":null,\"range\":[-10.0,10.0]},{\"key\":\"x29\",\"type\":\"Float\",\"default\":0.0,\"descritption\":null,\"range\":[-10.0,10.0]},{\"key\":\"x30\",\"type\":\"Float\",\"default\":0.0,\"descritption\":null,\"range\":[-10.0,10.0]},{\"key\":\"x31\",\"type\":\"Float\",\"default\":0.0,\"descritption\":null,\"range\":[-10.0,10.0]},{\"key\":\"x32\",\"type\":\"Float\",\"default\":0.0,\"descritption\":null,\"range\":[-10.0,10.0]},{\"key\":\"x33\",\"type\":\"Float\",\"default\":0.0,\"descritption\":null,\"range\":[-10.0,10.0]},{\"key\":\"x34\",\"type\":\"Float\",\"default\":0.0,\"descritption\":null,\"range\":[-10.0,10.0]},{\"key\":\"x35\",\"type\":\"Float\",\"default\":0.0,\"descritption\":null,\"range\":[-10.0,10.0]},{\"key\":\"x36\",\"type\":\"Float\",\"default\":0.0,\"descritption\":null,\"range\":[-10.0,10.0]},{\"key\":\"x37\",\"type\":\"Float\",\"default\":0.0,\"descritption\":null,\"range\":[-10.0,10.0]},{\"key\":\"x38\",\"type\":\"Float\",\"default\":0.0,\"descritption\":null,\"range\":[-10.0,10.0]},{\"key\":\"x39\",\"type\":\"Float\",\"default\":0.0,\"descritption\":null,\"range\":[-10.0,10.0]},{\"key\":\"x40\",\"type\":\"Float\",\"default\":0.0,\"descritption\":null,\"range\":[-10.0,10.0]},{\"key\":\"x41\",\"type\":\"Float\",\"default\":0.0,\"descritption\":null,\"range\":[-10.0,10.0]},{\"key\":\"x42\",\"type\":\"Float\",\"default\":0.0,\"descritption\":null,\"range\":[-10.0,10.0]},{\"key\":\"x43\",\"type\":\"Float\",\"default\":0.0,\"descritption\":null,\"range\":[-10.0,10.0]},{\"key\":\"x44\",\"type\":\"Float\",\"default\":0.0,\"descritption\":null,\"range\":[-10.0,10.0]},{\"key\":\"x45\",\"type\":\"Float\",\"default\":0.0,\"descritption\":null,\"range\":[-10.0,10.0]},{\"key\":\"x46\",\"type\":\"Float\",\"default\":0.0,\"descritption\":null,\"range\":[-10.0,10.0]},{\"key\":\"x47\",\"type\":\"Float\",\"default\":0.0,\"descritption\":null,\"range\":[-10.0,10.0]},{\"key\":\"x48\",\"type\":\"Float\",\"default\":0.0,\"descritption\":null,\"range\":[-10.0,10.0]},{\"key\":\"x49\",\"type\":\"Float\",\"default\":0.0,\"descritption\":null,\"range\":[-10.0,10.0]},{\"key\":\"x50\",\"type\":\"Float\",\"default\":0.0,\"descritption\":null,\"range\":[-10.0,10.0]},{\"key\":\"x51\",\"type\":\"Float\",\"default\":0.0,\"descritption\":null,\"range\":[-10.0,10.0]},{\"key\":\"x52\",\"type\":\"Float\",\"default\":0.0,\"descritption\":null,\"range\":[-10.0,10.0]},{\"key\":\"x53\",\"type\":\"Float\",\"default\":0.0,\"descritption\":null,\"range\":[-10.0,10.0]},{\"key\":\"x54\",\"type\":\"Float\",\"default\":0.0,\"descritption\":null,\"range\":[-10.0,10.0]},{\"key\":\"x55\",\"type\":\"Float\",\"default\":0.0,\"descritption\":null,\"range\":[-10.0,10.0]},{\"key\":\"x56\",\"type\":\"Float\",\"default\":0.0,\"descritption\":null,\"range\":[-10.0,10.0]},{\"key\":\"x57\",\"type\":\"Float\",\"default\":0.0,\"descritption\":null,\"range\":[-10.0,10.0]},{\"key\":\"x58\",\"type\":\"Float\",\"default\":0.0,\"descritption\":null,\"range\":[-10.0,10.0]},{\"key\":\"x59\",\"type\":\"Float\",\"default\":0.0,\"descritption\":null,\"range\":[-10.0,10.0]},{\"key\":\"x60\",\"type\":\"Float\",\"default\":0.0,\"descritption\":null,\"range\":[-10.0,10.0]},{\"key\":\"x61\",\"type\":\"Float\",\"default\":0.0,\"descritption\":null,\"range\":[-10.0,10.0]},{\"key\":\"x62\",\"type\":\"Float\",\"default\":0.0,\"descritption\":null,\"range\":[-10.0,10.0]}]","_target":"{\"Simulator\":\"54e55bf81d41c82c40000001\",\"Analyzer\":null,\"RunsCount\":10}","_seed":123456789}
