{
 "x0":[-3,3],
 "x1":[-3,3],
 "x2":[-3,3],
 "x3":[-3,3],
 "x4":[-3,3],
 "x5":[-3,3],
 "x6":[-3,3],
 "x7":[-3,3],
 "x8":[-3,3],
 "x9":[-3,3],
 "x10":[-3,3],
 "x11":[-3,3],
 "x12":[-3,3],
 "x13":[-3,3],
 "x14":[-3,3],
 "x15":[-3,3],
 "x16":[-3,3],
 "x17":[-3,3],
 "x18":[-3,3],
 "x19":[-3,3],
 "x20":[-3,3],
 "x21":[-3,3],
 "x22":[-3,3],
 "x23":[-3,3],
 "x24":[-3,3],
 "x25":[-3,3],
 "x26":[-3,3],
 "x27":[-3,3],
 "x28":[-3,3],
 "x29":[-3,3],
 "x30":[-3,3],
 "x31":[-3,3],
 "x32":[-3,3],
 "x33":[-3,3],
 "x34":[-3,3],
 "x35":[-3,3],
 "x36":[-3,3],
 "x37":[-3,3],
 "x38":[-3,3],
 "x39":[-3,3],
 "x40":[-3,3],
 "x41":[-3,3],
 "x42":[-3,3],
 "x43":[-3,3],
 "x44":[-3,3],
 "x45":[-3,3],
 "x46":[-3,3],
 "x47":[-3,3],
 "x48":[-3,3],
 "x49":[-3,3],
 "x50":[-3,3],
 "x51":[-3,3],
 "x52":[-3,3],
 "x53":[-3,3],
 "x54":[-3,3],
 "x55":[-3,3],
 "x56":[-3,3],
 "x57":[-3,3],
 "x58":[-3,3],
 "x59":[-3,3],
 "x60":[-3,3],
 "x61":[-3,3],
 "x62":[-3,3],
 "x63":[-3,3],
 "x64":[-3,3],
 "x65":[-3,3],
 "x66":[-3,3],
 "x67":[-3,3],
 "x68":[-3,3],
 "x69":[-3,3],
 "x70":[-3,3],
 "x71":[-3,3],
 "x72":[-3,3],
 "x73":[-3,3],
 "x74":[-3,3],
 "x75":[-3,3],
 "x76":[-3,3],
 "x77":[-3,3],
 "x78":[-3,3],
 "x79":[-3,3],
 "x80":[-3,3],
 "x81":[-3,3],
 "x82":[-3,3],
 "x83":[-3,3],
 "x84":[-3,3],
 "x85":[-3,3],
 "x86":[-3,3],
 "x87":[-3,3],
 "x88":[-3,3],
 "x89":[-3,3],
 "x90":[-3,3],
 "x91":[-3,3],
 "x92":[-3,3],
 "x93":[-3,3],
 "x94":[-3,3],
 "x95":[-3,3],
 "x96":[-3,3],
 "x97":[-3,3],
 "x98":[-3,3],
 "x99":[-3,3],
 "x100":[-3,3],
 "x101":[-3,3],
 "x102":[-3,3],
 "x103":[-3,3],
 "x104":[-3,3],
 "x105":[-3,3],
 "x106":[-3,3],
 "x107":[-3,3],
 "x108":[-3,3],
 "x109":[-3,3],
 "x110":[-3,3],
 "x111":[-3,3],
 "x112":[-3,3],
 "x113":[-3,3],
 "x114":[-3,3],
 "x115":[-3,3],
 "x116":[-3,3],
 "x117":[-3,3],
 "x118":[-3,3],
 "x119":[-3,3],
 "x120":[-3,3],
 "x121":[-3,3],
 "x122":[-3,3],
 "x123":[-3,3],
 "x124":[-3,3],
 "x125":[-3,3],
 "x126":[-3,3]
}
